module_reloadable/Module.py
module_reloadable/__init__.py
module_reloadable-0.0.2.dist-info/LICENSE
module_reloadable-0.0.2.dist-info/METADATA
module_reloadable-0.0.2.dist-info/WHEEL
module_reloadable-0.0.2.dist-info/top_level.txt
module_reloadable-0.0.2.dist-info/RECORD
