Metadata-Version: 2.1
Name: module-reloadable
Version: 0.0.2
Summary: Module Reloadable
Home-page: https://github.com/leonmaks/module_reloadable
Author: Leon Maksim
Author-email: le_ma_@mail.ru
License: UNKNOWN
Platform: UNKNOWN
Classifier: Programming Language :: Python :: 3
Classifier: License :: OSI Approved :: MIT License
Classifier: Operating System :: OS Independent
